pyopt_tools/__init__.py
pyopt_tools/colors.py
pyopt_tools/console.py
pyopt_tools/file_tools.py
pyopt_tools/listools.py
pyopt_tools/math_tools.py
pyopt_tools/pyvec.py
pyopt_tools/string_tools.py
pyopt_tools-0.7.dist-info/LICENCE
pyopt_tools-0.7.dist-info/METADATA
pyopt_tools-0.7.dist-info/WHEEL
pyopt_tools-0.7.dist-info/top_level.txt
pyopt_tools-0.7.dist-info/RECORD
