Metadata-Version: 2.1
Name: pyopt-tools
Version: 0.7
Summary: A Python package full of small & useful functions to make your life easier.
Home-page: UNKNOWN
Author: FUSEN
Author-email: fus3ngames@gmail.com
License: UNKNOWN
Keywords: python,pyopt-tools,python optimization tools,python mirco functions,string tools,math_tools,list_tool,pyvec
Platform: UNKNOWN
Classifier: Development Status :: 3 - Alpha
Classifier: Intended Audience :: Developers
Classifier: Programming Language :: Python :: 3
Classifier: Operating System :: Unix
Classifier: Operating System :: MacOS :: MacOS X
Classifier: Operating System :: Microsoft :: Windows
License-File: LICENCE
